[
    {
        "id": "7215957160189297434",
        "video_id": "7206917722318359835",
        "text": "en tưong 基本工资là lương cơ bản",
        "create_time": "2023-03-29T13:19:30",
        "digg_count": 1,
        "reply_total": 0,
        "user": {
            "id": "6624993996547227649",
            "region": "VN",
            "sec_uid": "MS4wLjABAAAAytb-6pky7gTaaOQsY5ZFhLiPx9zFaGgh4mg4Ux_httvWLdN-wYTY-VWUCxVxGmFI",
            "unique_id": "bong_be",
            "nickname": "bông bé",
            "signature": "",
            "avatar": "https://p16-useast2a.tiktokcdn.com/tos-useast2a-avt-0068-giso/555484aa73fbcb293ac79c8f6c5ee0ac~tplv-tiktokx-cropcenter-q:100:100:q75.jpeg?dr=10794&idc=maliva&nonce=20560&ps=87d6e48a&refresh_token=503e854e8fa43d1e2b85a4d6ea69f237&s=COMMENT_LIST&sc=avatar&shcp=ff37627b&shp=30310797&t=223449c4",
            "verified": false,
            "secret": true
        },
        "status": 1
    },
    {
        "id": "7216002650932151041",
        "video_id": "7206917722318359835",
        "text": "跨国公司",
        "create_time": "2023-03-29T16:15:59",
        "digg_count": 1,
        "reply_total": 0,
        "user": {
            "id": "6901178589116564482",
            "region": "VN",
            "sec_uid": "MS4wLjABAAAAnHst4l30T6BmJ9AJt7vx81LjovNgFM6Uk_fGhQ8Ckf8EHyLWHKqMtnHw2fkAyTdz",
            "unique_id": "huy20897",
            "nickname": "Shin",
            "signature": "",
            "avatar": "https://p16-sg.tiktokcdn.com/tos-alisg-avt-0068/2485752aaf321abd7acd0ac305d3cbb7~tplv-tiktokx-cropcenter-q:100:100:q80.jpeg?dr=10794&idc=maliva&nonce=5728&ps=87d6e48a&refresh_token=e4d4a4a053e8f21d0897af6cb4a3cb43&s=COMMENT_LIST&sc=avatar&shcp=ff37627b&shp=30310797&t=223449c4",
            "verified": false,
            "secret": true
        },
        "status": 1
    },
    {
        "id": "7216188045816955654",
        "video_id": "7206917722318359835",
        "text": "Da guo ja gong shi",
        "create_time": "2023-03-30T04:15:44",
        "digg_count": 1,
        "reply_total": 0,
        "user": {
            "id": "6582151754686038017",
            "region": "VN",
            "sec_uid": "MS4wLjABAAAAeIhqpbkwETR0TpPWFHtonFb5vnQu1vk2g7_U4D64XBj3V_5bF8I_neko-DX4DHxj",
            "unique_id": "bynnthu",
            "nickname": "Gđ bạn Voi Bản Đôn",
            "signature": "https://shp.ee/hejqzh4",
            "avatar": "https://p16-sg.tiktokcdn.com/tos-alisg-avt-0068/f9d0626ccdc187942d7631d81b745ca7~tplv-tiktokx-cropcenter-q:100:100:q80.jpeg?dr=10794&idc=maliva&nonce=21790&ps=87d6e48a&refresh_token=52844e1aa342b59e556cf63652966105&s=COMMENT_LIST&sc=avatar&shcp=ff37627b&shp=30310797&t=223449c4",
            "verified": false,
            "secret": false
        },
        "status": 1
    },
    {
        "id": "7207036173830767362",
        "video_id": "7206917722318359835",
        "text": "Cô ơi câu “chúc em hạnh phúc bên người em yêu” nói sao cô. Mong cô rep ạ🥰",
        "create_time": "2023-03-05T12:21:43",
        "digg_count": 1,
        "reply_total": 0,
        "user": {
            "id": "7030309005219218434",
            "region": "VN",
            "sec_uid": "MS4wLjABAAAA6cWumKUiznn2QUa3oTqYa8zxMOr4SuYbznq0PnyUieiaz12rgZ37JF6XHuXdvhVH",
            "unique_id": "hhtn9997",
            "nickname": "Thanh Nhi",
            "signature": "“Learn to be alone because not every one will stay”",
            "avatar": "https://p16-sg.tiktokcdn.com/tos-alisg-avt-0068/80937e7f05f044be9bf8f05ce12363fe~tplv-tiktokx-cropcenter-q:100:100:q80.jpeg?dr=10794&idc=maliva&nonce=73185&ps=87d6e48a&refresh_token=b18e090b0d07558ce5c4d9a4814b3a7b&s=COMMENT_LIST&sc=avatar&shcp=ff37627b&shp=30310797&t=223449c4",
            "verified": false,
            "secret": false
        },
        "status": 1
    },
    {
        "id": "7217294128215655195",
        "video_id": "7206917722318359835",
        "text": "跨国公司",
        "create_time": "2023-04-02T03:47:50",
        "digg_count": 1,
        "reply_total": 0,
        "user": {
            "id": "6705612564539573250",
            "region": "VN",
            "sec_uid": "MS4wLjABAAAA2GLM6ZJ5m9EugYWnAeRRFJq2M_dTSRo--ZnOc4kCAZFgL6efGXetKxtvyAQWDiaM",
            "unique_id": "plsdontrmd",
            "nickname": "Bao Quynh Tran",
            "signature": "",
            "avatar": "https://p16-sg.tiktokcdn.com/tos-alisg-avt-0068/6c14616a06cfff86a56c885482dd6e54~tplv-tiktokx-cropcenter-q:100:100:q80.jpeg?dr=10794&idc=maliva&nonce=70448&ps=87d6e48a&refresh_token=5bf2101306c6c8b22832dfb8f860858f&s=COMMENT_LIST&sc=avatar&shcp=ff37627b&shp=30310797&t=223449c4",
            "verified": false,
            "secret": true
        },
        "status": 1
    },
    {
        "id": "7207021519711716122",
        "video_id": "7206917722318359835",
        "text": "Cung sưa in tơ nấy sần nồ",
        "create_time": "2023-03-05T11:24:29",
        "digg_count": 1,
        "reply_total": 1,
        "user": {
            "id": "6824501515278369793",
            "region": "VN",
            "sec_uid": "MS4wLjABAAAAiR74mHew7KKEjVj9jtd8g95N0fhgc7CriVgtqNAlggUYc0T0zsBks6cneryeAB1u",
            "unique_id": "mr_ti_1986",
            "nickname": "Max Care",
            "signature": "Salon Kiều nhận làm nailbox theo yêu cầu.",
            "avatar": "https://p16-sg.tiktokcdn.com/tos-alisg-avt-0068/04d33217c98e7c41eb02fcef9a008a47~tplv-tiktokx-cropcenter-q:100:100:q80.jpeg?dr=10794&idc=maliva&nonce=37562&ps=87d6e48a&refresh_token=79ce997020a4737ae3b96c8e7548a970&s=COMMENT_LIST&sc=avatar&shcp=ff37627b&shp=30310797&t=223449c4",
            "verified": false,
            "secret": false
        },
        "status": 1
    },
    {
        "id": "7206949926357599003",
        "video_id": "7206917722318359835",
        "text": "跨国公司",
        "create_time": "2023-03-05T06:46:49",
        "digg_count": 1,
        "reply_total": 1,
        "user": {
            "id": "6635949751559667713",
            "region": "VN",
            "sec_uid": "MS4wLjABAAAAquewgI0v6jULonVZQw9vIygfox3fZppZyUwos3icj0dvooa2MkC0bDFXhpkrgSab",
            "unique_id": "volinh0803",
            "nickname": "Linlinvo",
            "signature": "",
            "avatar": "https://p16-sg.tiktokcdn.com/tos-alisg-avt-0068/34fc9f89c837f54ca3fa788be3fc4a90~tplv-tiktokx-cropcenter-q:100:100:q80.jpeg?dr=10794&idc=maliva&nonce=14188&ps=87d6e48a&refresh_token=2b6f0a49d7fc1d808e6c49a466eacc96&s=COMMENT_LIST&sc=avatar&shcp=ff37627b&shp=30310797&t=223449c4",
            "verified": false,
            "secret": false
        },
        "status": 1
    },
    {
        "id": "7219323046099534619",
        "video_id": "7206917722318359835",
        "text": "chị ơi hoàng mai thương thì nói như thế nào ạ mong c rep",
        "create_time": "2023-04-07T15:00:54",
        "digg_count": 1,
        "reply_total": 0,
        "user": {
            "id": "6820164171487151105",
            "region": "VN",
            "sec_uid": "MS4wLjABAAAAWVEVPevRm5eVUBN4kNlMCXl_pffn_eKAgyIFX_WlA0zAHrmY2BbSg5VE_PPJwEXD",
            "unique_id": "05_10_1994thuy.ana",
            "nickname": "Thủy ana",
            "signature": "No bio yet",
            "avatar": "https://p16-sg.tiktokcdn.com/tos-alisg-avt-0068/2185f6e8333aecf1a319691d6406ba3c~tplv-tiktokx-cropcenter-q:100:100:q80.jpeg?dr=10794&idc=maliva&nonce=62784&ps=87d6e48a&refresh_token=b642f3cb6959ed4117050260c6595174&s=COMMENT_LIST&sc=avatar&shcp=ff37627b&shp=30310797&t=223449c4",
            "verified": false,
            "secret": false
        },
        "status": 1
    },
    {
        "id": "7207680255124046618",
        "video_id": "7206917722318359835",
        "text": "佣金和回扣有什么区别",
        "create_time": "2023-03-07T06:00:48",
        "digg_count": 1,
        "reply_total": 0,
        "user": {
            "id": "6601670979854893058",
            "region": "VN",
            "sec_uid": "MS4wLjABAAAAOJSmo2a2Fv4K6uQWwvCjLiRo5KjlT-fwvqzYuGmBrhCEUl3mzh3EEbSZ-zDjr9TX",
            "unique_id": "bonghongcoguy",
            "nickname": "NingMengCha",
            "signature": "Miệng luôn tươi cười, may mắn tự nhiên đến 🍀",
            "avatar": "https://p16-sg.tiktokcdn.com/tos-alisg-avt-0068/f0dbe90e570205ace8a6528b6293bf49~tplv-tiktokx-cropcenter-q:100:100:q80.jpeg?dr=10794&idc=maliva&nonce=64220&ps=87d6e48a&refresh_token=9de7ed85ff3f8aef803496ace45c41af&s=COMMENT_LIST&sc=avatar&shcp=ff37627b&shp=30310797&t=223449c4",
            "verified": false,
            "secret": false
        },
        "status": 1
    },
    {
        "id": "7206934643978879771",
        "video_id": "7206917722318359835",
        "text": "多国家公司",
        "create_time": "2023-03-05T05:47:28",
        "digg_count": 1,
        "reply_total": 1,
        "user": {
            "id": "6673407204445881346",
            "region": "VN",
            "sec_uid": "MS4wLjABAAAAINRVTl90lBf5eQBlteJecKPq2zMMihwhl-Fn8E2rDO3VP518qTbg4Odtgbmf77lt",
            "unique_id": "31720208857gg",
            "nickname": "Quy Nguyen",
            "signature": "",
            "avatar": "https://p16-useast2a.tiktokcdn.com/tos-useast2a-avt-0068-giso/17b1ba74204caecb644da8505e7a203b~tplv-tiktokx-cropcenter-q:100:100:q75.jpeg?dr=10794&idc=maliva&nonce=67269&ps=87d6e48a&refresh_token=8f3f77e8e151a82a33e5d720041ae5d2&s=COMMENT_LIST&sc=avatar&shcp=ff37627b&shp=30310797&t=223449c4",
            "verified": false,
            "secret": true
        },
        "status": 1
    },
    {
        "id": "7219727449049907994",
        "video_id": "7206917722318359835",
        "text": "@Bé khôi",
        "create_time": "2023-04-08T17:10:13",
        "digg_count": 1,
        "reply_total": 0,
        "user": {
            "id": "6648234485026750466",
            "region": "VN",
            "sec_uid": "MS4wLjABAAAAM7ycpbxOFwPBSsnu7ek8-0_WX7QNyifdECSzZwIAF4ZIhIIORvhQB17TK3uLzOhW",
            "unique_id": "leuleulannua",
            "nickname": "Hạnh",
            "signature": "",
            "avatar": "https://p16-sg.tiktokcdn.com/tos-alisg-avt-0068/96cf9764821726a2dc2e82ae9761fc0b~tplv-tiktokx-cropcenter-q:100:100:q80.jpeg?dr=10794&idc=maliva&nonce=86295&ps=87d6e48a&refresh_token=f8bdfb427e0e7b8b06e809aad4eb759d&s=COMMENT_LIST&sc=avatar&shcp=ff37627b&shp=30310797&t=223449c4",
            "verified": false,
            "secret": false
        },
        "status": 1
    },
    {
        "id": "7219961294401061658",
        "video_id": "7206917722318359835",
        "text": "kuaguo gongsi-跨国公司",
        "create_time": "2023-04-09T08:17:46",
        "digg_count": 1,
        "reply_total": 0,
        "user": {
            "id": "7107839334933791746",
            "region": "VN",
            "sec_uid": "MS4wLjABAAAAnJxiHlgcvJd2DRhBczFI5m2970AHiZqQSqehklkDjRuVSjXL60terttFZooyfEg8",
            "unique_id": "daudau982022",
            "nickname": "ĐẬU ĐẬU 2022",
            "signature": "",
            "avatar": "https://p16-useast2a.tiktokcdn.com/tos-useast2a-avt-0068-giso/8e8fa4101068d3fcadb04def437bc25f~tplv-tiktokx-cropcenter-q:100:100:q75.jpeg?dr=10794&idc=maliva&nonce=34686&ps=87d6e48a&refresh_token=ea4bd0f1a43f7e53294919a5d435236f&s=COMMENT_LIST&sc=avatar&shcp=ff37627b&shp=30310797&t=223449c4",
            "verified": false,
            "secret": false
        },
        "status": 1
    },
    {
        "id": "7220482385459462917",
        "video_id": "7206917722318359835",
        "text": "🥰🥰",
        "create_time": "2023-04-10T17:59:33",
        "digg_count": 1,
        "reply_total": 0,
        "user": {
            "id": "6998536703255217154",
            "region": "TW",
            "sec_uid": "MS4wLjABAAAAO5f6Ue9Xv_OgsWIRnnehVHF9MHOslmCftX78Y6Nn22IXx0Gb4_ufz6tici2FYBSe",
            "unique_id": "vucuong2222",
            "nickname": "Vũ Cường",
            "signature": "",
            "avatar": "https://p16-sg.tiktokcdn.com/tos-alisg-avt-0068/e6ae0974221535f5ba1d2141c5df0727~tplv-tiktokx-cropcenter-q:100:100:q80.jpeg?dr=10794&idc=maliva&nonce=74464&ps=87d6e48a&refresh_token=6b4183d807886a02e1c5ec4b152689bf&s=COMMENT_LIST&sc=avatar&shcp=ff37627b&shp=30310797&t=223449c4",
            "verified": false,
            "secret": false
        },
        "status": 1
    },
    {
        "id": "7220580758770860827",
        "video_id": "7206917722318359835",
        "text": "@Yen_dung_HN",
        "create_time": "2023-04-11T00:21:57",
        "digg_count": 1,
        "reply_total": 0,
        "user": {
            "id": "7147326624702039042",
            "region": "CN",
            "sec_uid": "MS4wLjABAAAA_dQShBCkLC0RN2Rdl6Aoj_4Mo8GRCbDqkcvhV8LhwCAoe3UnqMO5R0gAellG2XZY",
            "unique_id": "user7818359875854",
            "nickname": "nghĩa 1993",
            "signature": "",
            "avatar": "https://p16-useast2a.tiktokcdn.com/tos-useast2a-avt-0068-giso/e0e02e60f0d111df636c81e445502664~tplv-tiktokx-cropcenter-q:100:100:q75.jpeg?dr=10794&idc=maliva&nonce=22219&ps=87d6e48a&refresh_token=44505e85c5c6bf0420c68c85b461c4fb&s=COMMENT_LIST&sc=avatar&shcp=ff37627b&shp=30310797&t=223449c4",
            "verified": false,
            "secret": false
        },
        "status": 1
    },
    {
        "id": "7220798988625822470",
        "video_id": "7206917722318359835",
        "text": "🥰🥰🥰",
        "create_time": "2023-04-11T14:28:11",
        "digg_count": 1,
        "reply_total": 0,
        "user": {
            "id": "7193579611513816065",
            "region": "TW",
            "sec_uid": "MS4wLjABAAAAbY6Vg5dQCbVwyZU78QsAVe0VciV66Z_6ibUNykmHFQ_E2vI9rCU2CuSz2WS51hxN",
            "unique_id": "thaizin1988",
            "nickname": "Zkt38",
            "signature": "",
            "avatar": "https://p16-amd-va.tiktokcdn.com/tos-maliva-avt-0068/22ba28eb6f208f6f537615c78058329f~tplv-tiktokx-cropcenter-q:100:100:q75.jpeg?dr=10794&idc=maliva&nonce=79137&ps=87d6e48a&refresh_token=05a4d8995af8d942518f9df8b9ddaae9&s=COMMENT_LIST&sc=avatar&shcp=ff37627b&shp=30310797&t=223449c4",
            "verified": false,
            "secret": false
        },
        "status": 1
    },
    {
        "id": "7220832710037062401",
        "video_id": "7206917722318359835",
        "text": "跨国公司",
        "create_time": "2023-04-11T16:39:00",
        "digg_count": 1,
        "reply_total": 0,
        "user": {
            "id": "6542473870044643329",
            "region": "KH",
            "sec_uid": "MS4wLjABAAAA1ykNGhpPvvSF04pJ9lBt_Z2dZfU-YKY8CYTv6Xz6CYprx5vWMvmHSwymUzfTVy8S",
            "unique_id": "zhengchinh9",
            "nickname": "chủ tịch",
            "signature": "",
            "avatar": "https://p16-sg.tiktokcdn.com/tos-alisg-avt-0068/5813a473f142e4e3d9021260171797d2~tplv-tiktokx-cropcenter-q:100:100:q80.jpeg?dr=10794&idc=maliva&nonce=69236&ps=87d6e48a&refresh_token=439b204755a3a22deb7e8a3f7533a578&s=COMMENT_LIST&sc=avatar&shcp=ff37627b&shp=30310797&t=223449c4",
            "verified": false,
            "secret": false
        },
        "status": 1
    },
    {
        "id": "7220866092406407963",
        "video_id": "7206917722318359835",
        "text": "中国人说保底多少",
        "create_time": "2023-04-11T18:49:02",
        "digg_count": 1,
        "reply_total": 0,
        "user": {
            "id": "7076970774263432194",
            "region": "VN",
            "sec_uid": "MS4wLjABAAAA08bMdCe_koaCV8lAxGElOSr5AiycsYgNtZx70UGcJPjloT2L1l-NdQmHV8cSIRjb",
            "unique_id": "user7708964222962",
            "nickname": "@李氏水",
            "signature": "cuộc sống vẫn cứ muôn màu muôn vẻ",
            "avatar": "https://p16-useast2a.tiktokcdn.com/tos-useast2a-avt-0068-giso/ef5f37a876061636db47a73b658ec56d~tplv-tiktokx-cropcenter-q:100:100:q75.jpeg?dr=10794&idc=maliva&nonce=48152&ps=87d6e48a&refresh_token=f6de502a6c64780c622d45d7b9abed63&s=COMMENT_LIST&sc=avatar&shcp=ff37627b&shp=30310797&t=223449c4",
            "verified": false,
            "secret": false
        },
        "status": 1
    },
    {
        "id": "7206932126498718490",
        "video_id": "7206917722318359835",
        "text": "😳😳😳",
        "create_time": "2023-03-05T05:37:38",
        "digg_count": 1,
        "reply_total": 0,
        "user": {
            "id": "6970589007520859138",
            "region": "TW",
            "sec_uid": "MS4wLjABAAAAXkRmNBam-qfMizaNGws4oa_HE5-85mtq6ZH_hsei7II15ZBABG13OwLpemslLR3p",
            "unique_id": "phamminhquangbinh",
            "nickname": "Minh QB",
            "signature": "mục tiêu  2000 fl",
            "avatar": "https://p16-amd-va.tiktokcdn.com/tos-maliva-avt-0068/91100943285b59f9af28e9cb0e2a8a01~tplv-tiktokx-cropcenter-q:100:100:q75.jpeg?dr=10794&idc=maliva&nonce=82522&ps=87d6e48a&refresh_token=73385e3212761ed89ef3067c765be6d5&s=COMMENT_LIST&sc=avatar&shcp=ff37627b&shp=30310797&t=223449c4",
            "verified": false,
            "secret": false
        },
        "status": 1
    },
    {
        "id": "7220943157286191877",
        "video_id": "7206917722318359835",
        "text": "跨國公司",
        "create_time": "2023-04-11T23:47:51",
        "digg_count": 1,
        "reply_total": 0,
        "user": {
            "id": "7060813864787231745",
            "region": "TW",
            "sec_uid": "MS4wLjABAAAAjSmC7CcOAmxwyEjjX4XN77XuRrOhA608cvR3JYNNMIjx_-anSvcQpSww2ByFOCRq",
            "unique_id": "htw_vn",
            "nickname": ".",
            "signature": "",
            "avatar": "https://p16-useast2a.tiktokcdn.com/tos-useast2a-avt-0068-giso/3b65d523e99950bbffece7e78e20434b~tplv-tiktokx-cropcenter-q:100:100:q75.jpeg?dr=10794&idc=maliva&nonce=74744&ps=87d6e48a&refresh_token=28018ea866643b6f402e750d7d72d6f2&s=COMMENT_LIST&sc=avatar&shcp=ff37627b&shp=30310797&t=223449c4",
            "verified": false,
            "secret": true
        },
        "status": 1
    },
    {
        "id": "7221141540214178561",
        "video_id": "7206917722318359835",
        "text": "🥰",
        "create_time": "2023-04-12T12:37:29",
        "digg_count": 1,
        "reply_total": 0,
        "user": {
            "id": "6917608258078049282",
            "region": "TW",
            "sec_uid": "MS4wLjABAAAAnbOkK2yC3YE4madXFHLYSkzskVxscUMrxzxQiT-wP30pQT3nrNav4ifYgxklBOp4",
            "unique_id": "nhungtruong_8.3",
            "nickname": "❤️HồngNhung🇹🇼🇻🇳",
            "signature": "Sống phải biết phấn đấu💪🏾💪🏾💪🏾",
            "avatar": "https://p16-sg.tiktokcdn.com/tos-alisg-avt-0068/71ce6b17bc0b88b1fbde7eafe0851a6b~tplv-tiktokx-cropcenter-q:100:100:q80.jpeg?dr=10794&idc=maliva&nonce=11440&ps=87d6e48a&refresh_token=045981265d1ecdad37ca5e5b83a1483d&s=COMMENT_LIST&sc=avatar&shcp=ff37627b&shp=30310797&t=223449c4",
            "verified": false,
            "secret": false
        },
        "status": 1
    },
    {
        "id": "7221173623401644807",
        "video_id": "7206917722318359835",
        "text": "hay",
        "create_time": "2023-04-12T14:42:00",
        "digg_count": 1,
        "reply_total": 0,
        "user": {
            "id": "6855476935163921410",
            "region": "TW",
            "sec_uid": "MS4wLjABAAAAJ6qRCy5B_aGpYIklxLh5GbW5UQ4ZKJHpyQnQ9KOAFurYMm28U7Yjb4cYva3ThtS_",
            "unique_id": "userkhoikhoikhoi",
            "nickname": "khói",
            "signature": "",
            "avatar": "https://p16-sg.tiktokcdn.com/tos-alisg-avt-0068/a3c2582ba37c4a04c6ebd19dad499ddc~tplv-tiktokx-cropcenter-q:100:100:q80.jpeg?dr=10794&idc=maliva&nonce=13433&ps=87d6e48a&refresh_token=dbe8a3cc1996d6f6d30b1b1f5932133a&s=COMMENT_LIST&sc=avatar&shcp=ff37627b&shp=30310797&t=223449c4",
            "verified": false,
            "secret": false
        },
        "status": 1
    },
    {
        "id": "7221184853696676634",
        "video_id": "7206917722318359835",
        "text": "南部话",
        "create_time": "2023-04-12T15:25:36",
        "digg_count": 1,
        "reply_total": 0,
        "user": {
            "id": "7142879914882286594",
            "region": "VN",
            "sec_uid": "MS4wLjABAAAAbduKY4mLpVPWo_pG1jZSeWLIo4yDNfZek2qsnVl-MUu5-MNgAWCgAUM0GLW0w9n9",
            "unique_id": "yangxi901216",
            "nickname": "yangxi901216",
            "signature": "",
            "avatar": "https://lh3.googleusercontent.com/a/AItbvmkQ2Yxdqc9dHGWgOquyyNQjekq-XYywKUoojxY=s300-c",
            "verified": false,
            "secret": false
        },
        "status": 1
    },
    {
        "id": "7206929314732851995",
        "video_id": "7206917722318359835",
        "text": "hay hay. xin đăng ký học 🥰🥰",
        "create_time": "2023-03-05T05:26:39",
        "digg_count": 1,
        "reply_total": 1,
        "user": {
            "id": "6893261297950770177",
            "region": "VN",
            "sec_uid": "MS4wLjABAAAA8WpFDDYIKI4GTfRCmI9DluV-FGeny9thJlnjVdeXESwu1cC6GS-CbPKeIJ96BR7o",
            "unique_id": "dangngocson99",
            "nickname": "Maison252",
            "signature": "",
            "avatar": "https://p16-useast2a.tiktokcdn.com/tos-useast2a-avt-0068-giso/486698627d3e2092475dd30aa533bb10~tplv-tiktokx-cropcenter-q:100:100:q75.jpeg?dr=10794&idc=maliva&nonce=55483&ps=87d6e48a&refresh_token=7eb4240ea16ab06ffc58f5b2609eeb58&s=COMMENT_LIST&sc=avatar&shcp=ff37627b&shp=30310797&t=223449c4",
            "verified": false,
            "secret": false
        },
        "status": 1
    },
    {
        "id": "7222315718456836890",
        "video_id": "7206917722318359835",
        "text": "佣金😂",
        "create_time": "2023-04-15T16:34:13",
        "digg_count": 1,
        "reply_total": 0,
        "user": {
            "id": "6557935974311133186",
            "region": "VN",
            "sec_uid": "MS4wLjABAAAAiVmFej85vAVl3zqoPecZs6ZlR55NwUZBK6TkCoMWEYZ-8rQHYKjx7Hdx16Fr_xsZ",
            "unique_id": "nguyenhuy_jerry",
            "nickname": "nguyễn huy 🇻🇳🇻🇳",
            "signature": "",
            "avatar": "https://p16-useast2a.tiktokcdn.com/tos-useast2a-avt-0068-giso/e05974e172e4a32f8993eea1519785b9~tplv-tiktokx-cropcenter-q:100:100:q75.jpeg?dr=10794&idc=maliva&nonce=79717&ps=87d6e48a&refresh_token=8e80f0a8073e5878f4a2df704c00e3f3&s=COMMENT_LIST&sc=avatar&shcp=ff37627b&shp=30310797&t=223449c4",
            "verified": false,
            "secret": false
        },
        "status": 1
    },
    {
        "id": "7222626353190175515",
        "video_id": "7206917722318359835",
        "text": "duô guo zhia gong si",
        "create_time": "2023-04-16T12:39:19",
        "digg_count": 1,
        "reply_total": 0,
        "user": {
            "id": "6967179298760459266",
            "region": "VN",
            "sec_uid": "MS4wLjABAAAA7Ml4SKQETC2OnIaW7A8JeroiRGdYwzXd9EqFJTmLZw-TwTvHfNxQvjtZQTNUfZVd",
            "unique_id": "user5505315334472",
            "nickname": "user5505315334472",
            "signature": "",
            "avatar": "https://p16-amd-va.tiktokcdn.com/musically-maliva-obj/1594805258216454~tplv-tiktokx-cropcenter-q:100:100:q75.jpeg?dr=10794&idc=maliva&nonce=87365&ps=87d6e48a&refresh_token=f6c1d146d28af84c66a80eac464978e3&s=COMMENT_LIST&sc=avatar&shcp=ff37627b&shp=30310797&t=223449c4",
            "verified": false,
            "secret": false
        },
        "status": 1
    },
    {
        "id": "7222716068170203930",
        "video_id": "7206917722318359835",
        "text": "hoa cúa cung sư,cty đa cuốc gia",
        "create_time": "2023-04-16T18:27:50",
        "digg_count": 1,
        "reply_total": 0,
        "user": {
            "id": "6827166804349223938",
            "region": "TW",
            "sec_uid": "MS4wLjABAAAA4SCzp7r44ELxqDAp8Rhy_ZZMymoFgWRdqwC6MsskKMiwfZg-M1LD-G0AkjradUiM",
            "unique_id": "nguyenlieu18051994",
            "nickname": "Nguyễn Liễu",
            "signature": "",
            "avatar": "https://p16-sg.tiktokcdn.com/tos-alisg-avt-0068/7323740554561323009~tplv-tiktokx-cropcenter-q:100:100:q80.jpeg?dr=10794&idc=maliva&nonce=48541&ps=87d6e48a&refresh_token=f59c53744b26f5f3c428c3a5476443c8&s=COMMENT_LIST&sc=avatar&shcp=ff37627b&shp=30310797&t=223449c4",
            "verified": false,
            "secret": false
        },
        "status": 1
    },
    {
        "id": "7206926220817449754",
        "video_id": "7206917722318359835",
        "text": "🥰🥰🥰",
        "create_time": "2023-03-05T05:14:42",
        "digg_count": 1,
        "reply_total": 0,
        "user": {
            "id": "6601977867821907970",
            "region": "TW",
            "sec_uid": "MS4wLjABAAAAMwYm2ywPxC5EBo7XkxfG1mE2gCNJ3m7ZsUQuTIqbT44sHotF6OpJ1vdxplF3s2PC",
            "unique_id": "nguyentrungnguye5",
            "nickname": "Trần Hoa",
            "signature": "",
            "avatar": "https://p16-amd-va.tiktokcdn.com/tos-maliva-avt-0068/6c02cdd8d925f37342ab6bcfd197ebce~tplv-tiktokx-cropcenter-q:100:100:q75.jpeg?dr=10794&idc=maliva&nonce=5794&ps=87d6e48a&refresh_token=8129082ff912791c524d8b7f938708cc&s=COMMENT_LIST&sc=avatar&shcp=ff37627b&shp=30310797&t=223449c4",
            "verified": false,
            "secret": false
        },
        "status": 1
    },
    {
        "id": "7225624979194250011",
        "video_id": "7206917722318359835",
        "text": "提成 tiền huê hồng",
        "create_time": "2023-04-24T14:35:35",
        "digg_count": 1,
        "reply_total": 0,
        "user": {
            "id": "6554451807304269825",
            "region": "VN",
            "sec_uid": "MS4wLjABAAAAnwqbPDLn40g7va9xvWGnVxucgeB6SXWVk5SiN7GQU2euAkoC7ZMvFPKxos1lpeLW",
            "unique_id": "botong1301",
            "nickname": "Nguyễn Lê Đan Kim",
            "signature": "",
            "avatar": "https://p16-sg.tiktokcdn.com/tos-alisg-avt-0068/7329274446168981525~tplv-tiktokx-cropcenter-q:100:100:q80.jpeg?dr=10794&idc=maliva&nonce=17536&ps=87d6e48a&refresh_token=2ff9e126a96eab2f4e44329f693124c5&s=COMMENT_LIST&sc=avatar&shcp=ff37627b&shp=30310797&t=223449c4",
            "verified": false,
            "secret": false
        },
        "status": 1
    },
    {
        "id": "7234142553183290118",
        "video_id": "7206917722318359835",
        "text": "@hiwangluan@",
        "create_time": "2023-05-17T13:27:53",
        "digg_count": 1,
        "reply_total": 0,
        "user": {
            "id": "62335186952",
            "region": "VN",
            "sec_uid": "MS4wLjABAAAA7YaDdm33veFU7P4TdLIR2rrqLD543FXHTcSvjeSDsQc",
            "unique_id": "w.h102",
            "nickname": "WH",
            "signature": "",
            "avatar": "https://p16-sg.tiktokcdn.com/tos-alisg-avt-0068/2f659816c6467a41d5ca7fa76be250c8~tplv-tiktokx-cropcenter-q:100:100:q80.jpeg?dr=10794&idc=maliva&nonce=11388&ps=87d6e48a&refresh_token=64efdaacd2c10fb8068547722cd43d2e&s=COMMENT_LIST&sc=avatar&shcp=ff37627b&shp=30310797&t=223449c4",
            "verified": false,
            "secret": false
        },
        "status": 1
    },
    {
        "id": "7227778494952293125",
        "video_id": "7206917722318359835",
        "text": "😞😞😞😱",
        "create_time": "2023-04-30T14:09:11",
        "digg_count": 0,
        "reply_total": 0,
        "user": {
            "id": "7222266077107192838",
            "region": "VN",
            "sec_uid": "MS4wLjABAAAAtMiXQP8OTK-5ktuuxyrCSqeSDAjgm9Za_0aZwrer88sV3IJR9zlm_yW-0emh-fVk",
            "unique_id": "user770605037139",
            "nickname": "user770605037139",
            "signature": "",
            "avatar": "https://p16-sg.tiktokcdn.com/tos-alisg-avt-0068/2f74367e6774146b91b973099dfbea05~tplv-tiktokx-cropcenter-q:100:100:q80.jpeg?dr=10794&idc=maliva&nonce=56870&ps=87d6e48a&refresh_token=d768d668f12fd6bad77306c9e6be774b&s=COMMENT_LIST&sc=avatar&shcp=ff37627b&shp=30310797&t=223449c4",
            "verified": false,
            "secret": false
        },
        "status": 1
    },
    {
        "id": "7230716225930838789",
        "video_id": "7206917722318359835",
        "text": "跨国公司",
        "create_time": "2023-05-08T07:52:01",
        "digg_count": 0,
        "reply_total": 0,
        "user": {
            "id": "6568617496327929857",
            "region": "VN",
            "sec_uid": "MS4wLjABAAAA3XPuRp31bsGOfv7c3izkxSYD_iJaBsF9simBqkadTzU52zXkQOfEf3DJZQVd2G2M",
            "unique_id": "eghilnuy02",
            "nickname": "Eghilnuy",
            "signature": "",
            "avatar": "https://p16-sg.tiktokcdn.com/tos-alisg-avt-0068/21c0d39e2e33fa06ff4ad98c63129e5b~tplv-tiktokx-cropcenter-q:100:100:q80.jpeg?dr=10794&idc=maliva&nonce=446&ps=87d6e48a&refresh_token=cb7efef34d3b13d633021d7430c30c76&s=COMMENT_LIST&sc=avatar&shcp=ff37627b&shp=30310797&t=223449c4",
            "verified": false,
            "secret": true
        },
        "status": 1
    },
    {
        "id": "7231413455805514498",
        "video_id": "7206917722318359835",
        "text": "sao lên đây toàn dạy ba cái này z trùi r mấy ng nghe k hiểu ngt hỏi câu nào trước r tl làm sao còn nếu nghe hieu d thì cung tl dc r mấy cha oi",
        "create_time": "2023-05-10T04:57:41",
        "digg_count": 0,
        "reply_total": 0,
        "user": {
            "id": "6723639138354693121",
            "region": "VN",
            "sec_uid": "MS4wLjABAAAAP4acXI2Xcw_CCqkrh3d7B4X3kZyzgt6bosShYqNZS0SpMXssTxkN7DbCZ35MRYM_",
            "unique_id": "user2fuy2rb4k3",
            "nickname": "Ngôi sao nhỏ",
            "signature": "Hành động chất lượng hơn lời nói😎",
            "avatar": "https://p16-useast2a.tiktokcdn.com/tos-useast2a-avt-0068-euttp/7323812262412550177~tplv-tiktokx-cropcenter-q:100:100:q75.jpeg?dr=10794&idc=maliva&nonce=51879&ps=87d6e48a&refresh_token=b07cae2294c23e19d8a66b02d8222150&s=COMMENT_LIST&sc=avatar&shcp=ff37627b&shp=30310797&t=223449c4",
            "verified": false,
            "secret": false
        },
        "status": 1
    },
    {
        "id": "7231887466780623622",
        "video_id": "7206917722318359835",
        "text": "🥰🥰🥰🥰🥰",
        "create_time": "2023-05-11T11:37:04",
        "digg_count": 0,
        "reply_total": 0,
        "user": {
            "id": "6982861837378257921",
            "region": "TW",
            "sec_uid": "MS4wLjABAAAAQQeueVkKFwa5PXR7lgsjqRJLmVdeTrzZUh9etVEglfBCRjcafu5eFRvHkKUqDk0L",
            "unique_id": "dyfmydr6ijfj",
            "nickname": "Phạm Điểm",
            "signature": "",
            "avatar": "https://p16-useast2a.tiktokcdn.com/tos-useast2a-avt-0068-giso/f9d2c9fda46ddc39910eb96d9d0f8d3b~tplv-tiktokx-cropcenter-q:100:100:q75.jpeg?dr=10794&idc=maliva&nonce=45919&ps=87d6e48a&refresh_token=2d2ab49e6fb9791003ddd199e3bed905&s=COMMENT_LIST&sc=avatar&shcp=ff37627b&shp=30310797&t=223449c4",
            "verified": false,
            "secret": false
        },
        "status": 1
    },
    {
        "id": "7232299231858770694",
        "video_id": "7206917722318359835",
        "text": "跨国公司",
        "create_time": "2023-05-12T14:14:53",
        "digg_count": 0,
        "reply_total": 0,
        "user": {
            "id": "6689388487240500226",
            "region": "VN",
            "sec_uid": "MS4wLjABAAAADQj7a4oUNLgZ084NDXG1EDmPZFrEBrJbF3L3JeYRujLrlD5F4XWj9q0DOmF7mmEv",
            "unique_id": "tienkchu",
            "nickname": "南进",
            "signature": "",
            "avatar": "https://p16-useast2a.tiktokcdn.com/tos-useast2a-avt-0068-giso/c8a039573bd9662dcc0acf05d349a459~tplv-tiktokx-cropcenter-q:100:100:q75.jpeg?dr=10794&idc=maliva&nonce=52410&ps=87d6e48a&refresh_token=825d5eb6f4f6928780233df34f09b1c1&s=COMMENT_LIST&sc=avatar&shcp=ff37627b&shp=30310797&t=223449c4",
            "verified": false,
            "secret": false
        },
        "status": 1
    },
    {
        "id": "7232521896184333062",
        "video_id": "7206917722318359835",
        "text": "跨国公司， cty đa quốc gia",
        "create_time": "2023-05-13T04:39:00",
        "digg_count": 0,
        "reply_total": 0,
        "user": {
            "id": "6939158352433955841",
            "region": "VN",
            "sec_uid": "MS4wLjABAAAAfsUPCa1SyyYRAJyn_KWR9Qmnzmb6GK_cbIzoGjJlC5g_DOsSWvvLK248UFy7N2i_",
            "unique_id": "tlongdichdao",
            "nickname": "TLong đi dịch dạo :)))",
            "signature": "",
            "avatar": "https://p16-useast2a.tiktokcdn.com/tos-useast2a-avt-0068-giso/bca14e5587c80ec19b821adeb9019737~tplv-tiktokx-cropcenter-q:100:100:q75.jpeg?dr=10794&idc=maliva&nonce=33473&ps=87d6e48a&refresh_token=c3d53021387cb24cc9273941cdd02fd3&s=COMMENT_LIST&sc=avatar&shcp=ff37627b&shp=30310797&t=223449c4",
            "verified": false,
            "secret": false
        },
        "status": 1
    },
    {
        "id": "7227034773251130118",
        "video_id": "7206917722318359835",
        "text": "@11.219",
        "create_time": "2023-04-28T09:46:09",
        "digg_count": 0,
        "reply_total": 0,
        "user": {
            "id": "6964775039405851650",
            "region": "VN",
            "sec_uid": "MS4wLjABAAAACWjNVg8JvoyqfWTdkTwBpDuF_Q8ObEuUktBorDKN3akcn8vqiaiHcG1-lRQ_oPYg",
            "unique_id": "do_tho06",
            "nickname": "Thờ",
            "signature": "",
            "avatar": "https://p16-sg.tiktokcdn.com/tos-alisg-avt-0068/61e7bef31de79124943008ccdb1869d7~tplv-tiktokx-cropcenter-q:100:100:q80.jpeg?dr=10794&idc=maliva&nonce=16954&ps=87d6e48a&refresh_token=7c5e7b877617948707fd39d697c94de1&s=COMMENT_LIST&sc=avatar&shcp=ff37627b&shp=30310797&t=223449c4",
            "verified": false,
            "secret": true
        },
        "status": 1
    },
    {
        "id": "7235222758526206725",
        "video_id": "7206917722318359835",
        "text": "跨国公司",
        "create_time": "2023-05-20T11:19:38",
        "digg_count": 0,
        "reply_total": 0,
        "user": {
            "id": "6812863182300300290",
            "region": "MY",
            "sec_uid": "MS4wLjABAAAAhGos_K1vMmBP7gwU_NcN64OwhpFNH0Kt1-Qeq4x3Gw0PtWxIxmeTMpe7-rmaNiQI",
            "unique_id": "ngoc2666666",
            "nickname": "Ngọc",
            "signature": "",
            "avatar": "https://p16-amd-va.tiktokcdn.com/tos-maliva-avt-0068/1b060078be43d48bbf90193447af9b75~tplv-tiktokx-cropcenter-q:100:100:q75.jpeg?dr=10794&idc=maliva&nonce=96631&ps=87d6e48a&refresh_token=f8b2e0b718e9d3a445b451e52154d846&s=COMMENT_LIST&sc=avatar&shcp=ff37627b&shp=30310797&t=223449c4",
            "verified": false,
            "secret": false
        },
        "status": 1
    },
    {
        "id": "7235558007298556678",
        "video_id": "7206917722318359835",
        "text": "dixin là lương thấp mà",
        "create_time": "2023-05-21T09:00:34",
        "digg_count": 0,
        "reply_total": 1,
        "user": {
            "id": "6691201424263463938",
            "region": "VN",
            "sec_uid": "MS4wLjABAAAAvNlV-0DLwZVeOLWuFKVbSFsHxJ9b1omekOTqcvewE--oz87dGUHeE_SKn2po2QmM",
            "unique_id": "codon1235566",
            "nickname": "KiếnChi Đỗ",
            "signature": "",
            "avatar": "https://p16-useast2a.tiktokcdn.com/tos-useast2a-avt-0068-giso/9f762cdc5e0dc4313d0f838f37857f8c~tplv-tiktokx-cropcenter-q:100:100:q75.jpeg?dr=10794&idc=maliva&nonce=81149&ps=87d6e48a&refresh_token=72fef652345763a3d56a02e3d861247f&s=COMMENT_LIST&sc=avatar&shcp=ff37627b&shp=30310797&t=223449c4",
            "verified": false,
            "secret": false
        },
        "status": 1
    },
    {
        "id": "7236023147652252417",
        "video_id": "7206917722318359835",
        "text": "những câu thuc sự hữu ích chị ơi hay và tuyệt vời lắm luôn",
        "create_time": "2023-05-22T15:05:37",
        "digg_count": 0,
        "reply_total": 0,
        "user": {
            "id": "6857804611550446593",
            "region": "VN",
            "sec_uid": "MS4wLjABAAAAuKLX5ZXPRmqWEeodMRudbi2DLbKutJYLbIoSH28_ll69Ab9jsLvcQJgWhBsUU0LH",
            "unique_id": "user89424593",
            "nickname": "牛肉面。",
            "signature": "发财发财",
            "avatar": "https://p16-sg.tiktokcdn.com/tos-alisg-avt-0068/08cb5624b6009aaaf6843dc67d75c3d6~tplv-tiktokx-cropcenter-q:100:100:q80.jpeg?dr=10794&idc=maliva&nonce=72419&ps=87d6e48a&refresh_token=f8075ffbd2cfcdcacb7073d32016ac20&s=COMMENT_LIST&sc=avatar&shcp=ff37627b&shp=30310797&t=223449c4",
            "verified": false,
            "secret": false
        },
        "status": 1
    },
    {
        "id": "7236066064563929862",
        "video_id": "7206917722318359835",
        "text": "🥰",
        "create_time": "2023-05-22T17:52:11",
        "digg_count": 0,
        "reply_total": 0,
        "user": {
            "id": "6865571401359049730",
            "region": "VN",
            "sec_uid": "MS4wLjABAAAAhkhs48ZipEMaT-D3X1K-sg6epNtJKUJcpLefjzRMOG9lmLNvCUykY7inznbgmci-",
            "unique_id": "anhngnsheshh",
            "nickname": "Anhnguyen",
            "signature": "欢迎你来这儿❤️❤️❤️...",
            "avatar": "https://p16-amd-va.tiktokcdn.com/tos-maliva-avt-0068/620c22b2c699de71a5abddb473a8c783~tplv-tiktokx-cropcenter-q:100:100:q75.jpeg?dr=10794&idc=maliva&nonce=47022&ps=87d6e48a&refresh_token=e68b2c286eb5ef35eca8c4483eed91bc&s=COMMENT_LIST&sc=avatar&shcp=ff37627b&shp=30310797&t=223449c4",
            "verified": false,
            "secret": false
        },
        "status": 1
    },
    {
        "id": "7236830848330695429",
        "video_id": "7206917722318359835",
        "text": "公視大國家",
        "create_time": "2023-05-24T19:19:59",
        "digg_count": 0,
        "reply_total": 0,
        "user": {
            "id": "6948304159717753858",
            "region": "TW",
            "sec_uid": "MS4wLjABAAAA45evmkjJZVx_uQeWRQ99HjIbsA5G_lruhhhvnqo_4tSH2xtk-YaehP8PC8GD5TYU",
            "unique_id": "huytran131189",
            "nickname": "huytran131189",
            "signature": "",
            "avatar": "https://p16-useast2a.tiktokcdn.com/tos-useast2a-avt-0068-giso/c3cd4884d1a0dd3d47ace3a52c3274c3~tplv-tiktokx-cropcenter-q:100:100:q75.jpeg?dr=10794&idc=maliva&nonce=93931&ps=87d6e48a&refresh_token=d4db8185a2f310225d8b7ec2445906a7&s=COMMENT_LIST&sc=avatar&shcp=ff37627b&shp=30310797&t=223449c4",
            "verified": false,
            "secret": false
        },
        "status": 1
    },
    {
        "id": "7207396854195503898",
        "video_id": "7206917722318359835",
        "text": "hay quá ạ 🥰",
        "create_time": "2023-03-06T11:41:05",
        "digg_count": 0,
        "reply_total": 0,
        "user": {
            "id": "6935347838511596545",
            "region": "TW",
            "sec_uid": "MS4wLjABAAAAfKgQxbKXpAMtu3gLFQC_BfgR40rx9Q7zb3oWHXwtvyFN2yXRcEQS3GLPpIXSE0Xu",
            "unique_id": "dy0nyzkh7vbb",
            "nickname": "dy0nyzkh7vbb",
            "signature": "",
            "avatar": "https://p16-sg.tiktokcdn.com/tos-alisg-avt-0068/7334122569424961557~tplv-tiktokx-cropcenter-q:100:100:q80.jpeg?dr=10794&idc=maliva&nonce=88117&ps=87d6e48a&refresh_token=a407274ea55b34f2f3920fbc62c985cf&s=COMMENT_LIST&sc=avatar&shcp=ff37627b&shp=30310797&t=223449c4",
            "verified": false,
            "secret": false
        },
        "status": 1
    }
]